FPGA/user/src/schmitt_trigger.v
module schmitt_trigger #(
    parameter WD = 14
) (
    input                  clk,
    input                  rstn,
    input  signed [WD-1:0] D,
    input  signed [WD-1:0] threshold,
    output reg             Q
);

  reg signed [WD-1:0] prev_Q;

  always @(posedge clk or negedge rstn) begin
    if (~rstn) begin
      Q      <= 0;
      prev_Q <= 0;
    end
    else begin
      if (D > threshold && prev_Q == 1'b0) begin
        Q <= 1'b1;  // Trigger on rising edge
      end
      else if (D < -threshold && prev_Q == 1'b1) begin
        Q <= 1'b0;  // Trigger on falling edge
      end
      prev_Q <= Q;  // Store previous value of Q
    end
  end

endmodule  //schmitt_trigger

FPGA/user/src/freq_cnt.v
module freq_cnt #(
    parameter WD = 14
) (
    input                  clk,
    input                  rstn,
    input  signed [WD-1:0] signal_in,
    input  signed [WD-1:0] threshold,
    output reg    [  31:0] cnt_out
);

  reg        prev_Q;
  reg [31:0] cnt;

  schmitt_trigger #(
      .WD(WD)
  ) u_schmitt_trigger (
      .clk      (clk),
      .rstn     (rstn),
      .D        (signal_in),
      .threshold(threshold),
      .Q        (Q)
  );

  always @(posedge clk or negedge rstn) begin
    if (~rstn) begin
      prev_Q  <= 'b0;
      cnt     <= 'b0;
      cnt_out <= 'b0;
    end
    else begin
      prev_Q <= Q;
      if (Q && (~prev_Q)) begin
        cnt     <= 'b0;
        cnt_out <= cnt;
      end
      else cnt <= cnt + 1;
    end
  end

endmodule  //freq_count

FPGA/user/sim/tb_freq_cnt.v
`timescale 1ns / 1ps

module tb_freq_cnt;
  // 参数定义
  parameter WD = 14;  // 数据位宽
  parameter CLK_PERIOD = 10;  // 10ns时钟周期 (100MHz)
  parameter SIN_PERIOD = 100;  // 正弦波周期1μs
  parameter SIM_TIME = 10000;  // 仿真时间10μs
  parameter NOISE_AMPLITUDE = 200;  // 噪声幅度
  // parameter THRESHOLD = 2000;  // 施密特触发器阈值


  // 信号声明
  reg                 clk;
  reg                 rstn;
  reg signed [WD-1:0] input_signal;

  // 内部变量
  real                sin_value;
  reg signed [WD-1:0] noise;
  reg signed [WD-1:0] clean_sine;
  integer             i;

  // 实例化被测单元
  wire       [  31:0] cnt;

  freq_cnt #(
      .WD(WD)
  ) u_freq_cnt (
      .clk      (clk),
      .rstn     (rstn),
      .signal_in(input_signal),
      .threshold(1000),
      .cnt_out  (cnt)
  );


  // 生成时钟
  initial begin
    clk = 0;
    forever #(CLK_PERIOD / 2) clk = ~clk;
  end

  // 生成复位信号
  initial begin
    rstn = 0;
    #(CLK_PERIOD * 5) rstn = 1;  // 5个时钟周期后释放复位
  end

  // 生成正弦波加噪声输入
  initial begin
    input_signal = 0;

    // 等待复位完成
    #(CLK_PERIOD * 10);

    // 生成10个周期的正弦波
    for (i = 0; i < SIM_TIME; i = i + 1) begin
      // 计算正弦值 (振幅约为32767/4 = 8191/4)
      sin_value    = $sin(2.0 * 3.14159 * i / SIN_PERIOD) * 2000;
      clean_sine   = $rtoi(sin_value);

      // 生成随机噪声
      noise        = ($random % (2 * NOISE_AMPLITUDE)) - NOISE_AMPLITUDE;

      // 将正弦波和噪声相加
      input_signal = clean_sine + noise;

      // 确保信号不超出范围
      if (input_signal > 2 ** (WD - 1) - 1) input_signal = 2 ** (WD - 1) - 1;
      else if (input_signal < -(2 ** (WD - 1))) input_signal = -(2 ** (WD - 1));

      #CLK_PERIOD;
    end
  end

  // 结束仿真
  initial begin
    #(SIM_TIME * CLK_PERIOD);
    $display("Simulation completed");
    $finish;
  end

  // 波形输出
  initial begin
    $dumpfile("./user/sim/tb_freq_cnt.vcd");
    $dumpvars(0, tb_freq_cnt);
  end

  // 结果监控
  always @(posedge clk) begin
    if (rstn) begin
      $display("Time: %t, Input: %d, cnt: %d, Clean Sine: %d", $time, input_signal, cnt, clean_sine);
    end
  end

endmodule

FPGA/user/sim/tb_freq_cnt.vcd
$date
	Sun Jun 01 14:07:56 2025
$end
$version
	Icarus Verilog
$end
$timescale
	1ps
$end
$scope module tb_freq_cnt $end
$var wire 32 ! cnt [31:0] $end
$var parameter 32 " CLK_PERIOD $end
$var parameter 32 # NOISE_AMPLITUDE $end
$var parameter 32 $ SIM_TIME $end
$var parameter 32 % SIN_PERIOD $end
$var parameter 32 & WD $end
$var reg 14 ' clean_sine [13:0] $end
$var reg 1 ( clk $end
$var reg 14 ) input_signal [13:0] $end
$var reg 14 * noise [13:0] $end
$var reg 1 + rstn $end
$var integer 32 , i [31:0] $end
$var real 1 - sin_value $end
$scope module u_freq_cnt $end
$var wire 1 ( clk $end
$var wire 1 + rstn $end
$var wire 14 . signal_in [13:0] $end
$var wire 14 / threshold [13:0] $end
$var wire 1 0 Q $end
$var parameter 32 1 WD $end
$var reg 32 2 cnt [31:0] $end
$var reg 32 3 cnt_out [31:0] $end
$var reg 1 4 prev_Q $end
$scope module u_schmitt_trigger $end
$var wire 14 5 D [13:0] $end
$var wire 1 ( clk $end
$var wire 1 + rstn $end
$var wire 14 6 threshold [13:0] $end
$var parameter 32 7 WD $end
$var reg 1 0 Q $end
$var reg 14 8 prev_Q [13:0] $end
$upscope $end
$upscope $end
$upscope $end
$enddefinitions $end
$comment Show the parameter values. $end
$dumpall
b1110 7
b1110 1
b1110 &
b1100100 %
b10011100010000 $
b11001000 #
b1010 "
$end
#0
$dumpvars
b0 8
b1111101000 6
b0 5
04
b0 3
b0 2
00
b1111101000 /
b0 .
r0 -
bx ,
0+
bx *
b0 )
0(
bx '
b0 !
$end
#5000
1(
#10000
0(
#15000
1(
#20000
0(
#25000
1(
#30000
0(
#35000
1(
#40000
0(
#45000
1(
#50000
0(
1+
#55000
b1 2
1(
#60000
0(
#65000
b10 2
1(
#70000
0(
#75000
b11 2
1(
#80000
0(
#85000
b100 2
1(
#90000
0(
#95000
b101 2
1(
#100000
0(
b11111111001100 )
b11111111001100 .
b11111111001100 5
b11111111001100 *
b0 '
b0 ,
#105000
b110 2
1(
#110000
0(
b11111000100110 )
b11111000100110 .
b11111000100110 5
b11110110101001 *
b1111101 '
r125.580933124485 -
b1 ,
#115000
b111 2
1(
#120000
0(
b1011 )
b1011 .
b1011 5
b11111100010001 *
b11111010 '
r250.6662565153715 -
b10 ,
#125000
b1000 2
1(
#130000
0(
b1000001 )
b1000001 .
b1000001 5
b11111011001011 *
b101110110 '
r374.7623163809537 -
b11 ,
#135000
b1001 2
1(
#140000
0(
b111000110 )
b111000110 .
b111000110 5
b11111111010101 *
b111110001 '
r497.3793630941158 -
b100 ,
#145000
b1010 2
1(
#150000
0(
b1000111111 )
b1000111111 .
b1000111111 5
b1001101010 '
r618.0334840071002 -
b101 ,
#155000
b1011 2
1(
#160000
0(
b101101101 )
b101101101 .
b101101101 5
b11111010001101 *
b1011100000 '
r736.2485132304241 -
b110 ,
#165000
b1100 2
1(
#170000
0(
b1001111101 )
b1001111101 .
b1001111101 5
b11111100101010 *
b1101010011 '
r851.5579108389337 -
b111 ,
#175000
b1101 2
1(
#180000
0(
b1110011100 )
b1110011100 .
b1110011100 5
b11111111011001 *
b1111000011 '
r963.5066040886358 -
b1000 ,
#185000
b1110 2
1(
#190000
0(
b1110000100 )
b1110000100 .
b1110000100 5
b11111101010101 *
b10000101111 '
r1071.652783377883 -
b1001 ,
#195000
b1111 2
1(
#200000
0(
b10001000101 )
b10001000101 .
b10001000101 5
b11111110101110 *
b10010010111 '
r1175.569645865085 -
b1010 ,
#205000
b10000 2
10
1(
#210000
0(
b10110111111 )
b10110111111 .
b10110111111 5
b11000101 *
b10011111010 '
r1274.847079861688 -
b1011 ,
#215000
b1 8
b10000 !
b10000 3
b0 2
14
1(
#220000
0(
b10010101110 )
b10010101110 .
b10010101110 5
b11111101010101 *
b10101011001 '
r1369.093283352919 -
b1100 ,
#225000
b1 2
1(
#230000
0(
b10011110101 )
b10011110101 .
b10011110101 5
b11111101000100 *
b10110110001 '
r1457.936310258725 -
b1101 ,
#235000
b10 2
1(
#240000
0(
b10110010110 )
b10110010110 .
b10110010110 5
b11111110010001 *
b11000000101 '
r1541.025538332549 -
b1110 ,
#245000
b11 2
1(
#250000
0(
b10011100000 )
b10011100000 .
b10011100000 5
b11111010001110 *
b11001010010 '
r1618.033052904814 -
b1111 ,
#255000
b100 2
1(
#260000
0(
b10010100101 )
b10010100101 .
b10010100101 5
b11111000001101 *
b11010011000 '
r1688.654941010132 -
b10000 ,
#265000
b101 2
1(
#270000
0(
b10010011010 )
b10010011010 .
b10010011010 5
b11110111000010 *
b11011011000 '
r1752.612490790904 -
b10001 ,
#275000
b110 2
1(
#280000
0(
b11010011110 )
b11010011110 .
b11010011110 5
b11111110001101 *
b11100010001 '
r1809.653291443834 -
b10010 ,
#285000
b111 2
1(
#290000
0(
b11001010010 )
b11001010010 .
b11001010010 5
b11111100001111 *
b11101000011 '
r1859.552229368375 -
b10011 ,
#295000
b1000 2
1(
#300000
0(
b10101111000 )
b10101111000 .
b10101111000 5
b11111000001010 *
b11101101110 '
r1902.112376585762 -
b10100 ,
#305000
b1001 2
1(
#310000
0(
b11110111000 )
b11110111000 .
b11110111000 5
b100111 *
b11110010001 '
r1937.165767922464 -
b10101 ,
#315000
b1010 2
1(
#320000
0(
b100001100110 )
b100001100110 .
b100001100110 5
b10111010 *
b11110101100 '
r1964.574063890872 -
b10110 ,
#325000
b1011 2
1(
#330000
0(
b11001100110 )
b11001100110 .
b11001100110 5
b11111010100110 *
b11111000000 '
r1984.229096651127 -
b10111 ,
#335000
b1100 2
1(
#340000
0(
b10110111100 )
b10110111100 .
b10110111100 5
b11110111110000 *
b11111001100 '
r1996.053296899453 -
b11000 ,
#345000
b1101 2
1(
#350000
0(
b11011011100 )
b11011011100 .
b11011011100 5
b11111100001101 *
b11111001111 '
r1999.99999999824 -
b11001 ,
#355000
b1110 2
1(
#360000
0(
b100000100000 )
b100000100000 .
b100000100000 5
b1010100 *
b11111001100 '
r1996.053630139736 -
b11010 ,
#365000
b1111 2
1(
#370000
0(
b11011110101 )
b11011110101 .
b11011110101 5
b11111100110101 *
b11111000000 '
r1984.229761816547 -
b11011 ,
#375000
b10000 2
1(
#380000
0(
b11010100001 )
b11010100001 .
b11010100001 5
b11111011110101 *
b11110101100 '
r1964.575058356329 -
b11100 ,
#385000
b10001 2
1(
#390000
0(
b11001011110 )
b11001011110 .
b11001011110 5
b11111011001101 *
b11110010001 '
r1937.167087763266 -
b11101 ,
#395000
b10010 2
1(
#400000
0(
b10111111001 )
b10111111001 .
b10111111001 5
b11111010001011 *
b11101101110 '
r1902.114016593107 -
b11110 ,
#405000
b10011 2
1(
#410000
0(
b11011010101 )
b11011010101 .
b11011010101 5
b11111110010010 *
b11101000011 '
r1859.554183069915 -
b11111 ,
#415000
b10100 2
1(
#420000
0(
b10011011001 )
b10011011001 .
b10011011001 5
b11110111001000 *
b11100010001 '
r1809.655551129215 -
b100000 ,
#425000
b10101 2
1(
#430000
0(
b11101100000 )
b11101100000 .
b11101100000 5
b10001000 *
b11011011000 '
r1752.615047542194 -
b100001 ,
#435000
b10110 2
1(
#440000
0(
b11100001010 )
b11100001010 .
b11100001010 5
b1110010 *
b11010011000 '
r1688.65778473702 -
b100010 ,
#445000
b10111 2
1(
#450000
0(
b10001110111 )
b10001110111 .
b10001110111 5
b11111000100101 *
b11001010010 '
r1618.036172384428 -
b100011 ,
#455000
b11000 2
1(
#460000
0(
b10011110011 )
b10011110011 .
b10011110011 5
b11111011101110 *
b11000000101 '
r1541.028921253748 -
b100100 ,
#465000
b11001 2
1(
#470000
0(
b1101111100 )
b1101111100 .
b1101111100 5
b11110111001011 *
b10110110001 '
r1457.939943270688 -
b100101 ,
#475000
b11010 2
1(
#480000
0(
b10001101110 )
b10001101110 .
b10001101110 5
b11111100010101 *
b10101011001 '
r1369.097152117831 -
b100110 ,
#485000
b11011 2
1(
#490000
0(
b10000100101 )
b10000100101 .
b10000100101 5
b11111100101011 *
b10011111010 '
r1274.851169111328 -
b100111 ,
#495000
b11100 2
1(
#500000
0(
b10001101010 )
b10001101010 .
b10001101010 5
b11111111010011 *
b10010010111 '
r1175.573939461079 -
b101000 ,
#505000
b11101 2
1(
#510000
0(
b1101011100 )
b1101011100 .
b1101011100 5
b11111100101101 *
b10000101111 '
r1071.6572643754 -
b101001 ,
#515000
b11110 2
1(
#520000
0(
b1001011101 )
b1001011101 .
b1001011101 5
b11111010011010 *
b1111000011 '
r963.5112548032531 -
b101010 ,
#525000
b11111 2
1(
#530000
0(
b1000011001 )
b1000011001 .
b1000011001 5
b11111011000110 *
b1101010011 '
r851.5627129164372 -
b101011 ,
#535000
b100000 2
1(
#540000
0(
b1110010101 )
b1110010101 .
b1110010101 5
b10110101 *
b1011100000 '
r736.2534477192398 -
b101100 ,
#545000
b100001 2
1(
#550000
0(
b110010001 )
b110010001 .
b110010001 5
b11111100100111 *
b1001101010 '
r618.0385314330887 -
b101101 ,
#555000
b100010 2
1(
#560000
0(
b110111100 )
b110111100 .
b110111100 5
b11111111001011 *
b111110001 '
r497.3845035374257 -
b101110 ,
#565000
b100011 2
1(
#570000
0(
b101011000 )
b101011000 .
b101011000 5
b11111111100010 *
b101110110 '
r374.7675295546377 -
b101111 ,
#575000
b100100 2
1(
#580000
0(
b11111101001100 )
b11111101001100 .
b11111101001100 5
b11111001010010 *
b11111010 '
r250.6715218454504 -
b110000 ,
#585000
b100101 2
1(
#590000
0(
b11111000110001 )
b11111000110001 .
b11111000110001 5
b11110110110100 *
b1111101 '
r125.5862298311408 -
b110001 ,
#595000
b100110 2
1(
#600000
0(
b1101010 )
b1101010 .
b1101010 5
b1101010 *
b0 '
r0.005307179586705452 -
b110010 ,
#605000
b100111 2
1(
#610000
0(
b101 )
b101 .
b101 5
b10000010 *
b11111110000011 '
r-125.5756364169452 -
b110011 ,
#615000
b101000 2
1(
#620000
0(
b11111100111111 )
b11111100111111 .
b11111100111111 5
b111001 *
b11111100000110 '
r-250.6609911835274 -
b110100 ,
#625000
b101001 2
1(
#630000
0(
b11110000111010 )
b11110000111010 .
b11110000111010 5
b11110110110000 *
b11111010001010 '
r-374.7571032046304 -
b110101 ,
#635000
b101010 2
1(
#640000
0(
b11110101101111 )
b11110101101111 .
b11110101101111 5
b11111101100000 *
b11111000001111 '
r-497.3742226473037 -
b110110 ,
#645000
b101011 2
1(
#650000
0(
b11101111010111 )
b11101111010111 .
b11101111010111 5
b11111001000001 *
b11110110010110 '
r-618.0284365767601 -
b110111 ,
#655000
00
b101100 2
1(
#660000
0(
b11110001110011 )
b11110001110011 .
b11110001110011 5
b11111101010011 *
b11110100100000 '
r-736.2435787364234 -
b111000 ,
#665000
b101101 2
04
b0 8
1(
#670000
0(
b11110010001011 )
b11110010001011 .
b11110010001011 5
b11111111011110 *
b11110010101101 '
r-851.5531087554335 -
b111001 ,
#675000
b101110 2
1(
#680000
0(
b11110010111011 )
b11110010111011 .
b11110010111011 5
b1111110 *
b11110000111101 '
r-963.501953367234 -
b111010 ,
#685000
b101111 2
1(
#690000
0(
b11110000100111 )
b11110000100111 .
b11110000100111 5
b1010110 *
b11101111010001 '
r-1071.648302372821 -
b111011 ,
#695000
b110000 2
1(
#700000
0(
b11101000011101 )
b11101000011101 .
b11101000011101 5
b11111010110100 *
b11101101101001 '
r-1175.565352260812 -
b111100 ,
#705000
b110001 2
1(
#710000
0(
b11101111001000 )
b11101111001000 .
b11101111001000 5
b11000010 *
b11101100000110 '
r-1274.842990603072 -
b111101 ,
#715000
b110010 2
1(
#720000
0(
b11100010111010 )
b11100010111010 .
b11100010111010 5
b11111000010011 *
b11101010100111 '
r-1369.089414578367 -
b111110 ,
#725000
b110011 2
1(
#730000
0(
b11100101001000 )
b11100101001000 .
b11100101001000 5
b11111011111001 *
b11101001001111 '
r-1457.932677236496 -
b111111 ,
#735000
b110100 2
1(
#740000
0(
b11101010001000 )
b11101010001000 .
b11101010001000 5
b10001101 *
b11100111111011 '
r-1541.022155400498 -
b1000000 ,
#745000
b110101 2
1(
#750000
0(
b11100110010101 )
b11100110010101 .
b11100110010101 5
b11111111100111 *
b11100110101110 '
r-1618.029933413808 -
b1000001 ,
#755000
b110110 2
1(
#760000
0(
b11100010011011 )
b11100010011011 .
b11100010011011 5
b11111100110011 *
b11100101101000 '
r-1688.652097271354 -
b1000010 ,
#765000
b110111 2
1(
#770000
0(
b11100111101010 )
b11100111101010 .
b11100111101010 5
b11000010 *
b11100100101000 '
r-1752.609934027272 -
b1000011 ,
#775000
b111000 2
1(
#780000
0(
b11011011000101 )
b11011011000101 .
b11011011000101 5
b11110111010110 *
b11100011101111 '
r-1809.651031745711 -
b1000100 ,
#785000
b111001 2
1(
#790000
0(
b11100001011010 )
b11100001011010 .
b11100001011010 5
b11111110011101 *
b11100010111101 '
r-1859.550275653741 -
b1000101 ,
#795000
b111010 2
1(
#800000
0(
b11100100101011 )
b11100100101011 .
b11100100101011 5
b10011001 *
b11100010010010 '
r-1902.110736565023 -
b1000110 ,
#805000
b111011 2
1(
#810000
0(
b11100100010000 )
b11100100010000 .
b11100100010000 5
b10100001 *
b11100001101111 '
r-1937.164448068022 -
b1000111 ,
#815000
b111100 2
1(
#820000
0(
b11011110101110 )
b11011110101110 .
b11011110101110 5
b11111101011010 *
b11100001010100 '
r-1964.573069411581 -
b1001000 ,
#825000
b111101 2
1(
#830000
0(
b11100011010100 )
b11100011010100 .
b11100011010100 5
b10010100 *
b11100001000000 '
r-1984.228431471735 -
b1001001 ,
#835000
b111110 2
1(
#840000
0(
b11011110111011 )
b11011110111011 .
b11011110111011 5
b11111110000111 *
b11100000110100 '
r-1996.052963645116 -
b1001010 ,
#845000
b111111 2
1(
#850000
0(
b11100001101000 )
b11100001101000 .
b11100001101000 5
b110111 *
b11100000110001 '
r-1999.999999984156 -
b1001011 ,
#855000
b1000000 2
1(
#860000
0(
b11011111100100 )
b11011111100100 .
b11011111100100 5
b11111110110000 *
b11100000110100 '
r-1996.053963365963 -
b1001100 ,
#865000
b1000001 2
1(
#870000
0(
b11011011011111 )
b11011011011111 .
b11011011011111 5
b11111010011111 *
b11100001000000 '
r-1984.230426967995 -
b1001101 ,
#875000
b1000010 2
1(
#880000
0(
b11011000101011 )
b11011000101011 .
b11011000101011 5
b11110111010111 *
b11100001010100 '
r-1964.576052807953 -
b1001110 ,
#885000
b1000011 2
1(
#890000
0(
b11011100100011 )
b11011100100011 .
b11011100100011 5
b11111010110100 *
b11100001101111 '
r-1937.168407590426 -
b1001111 ,
#895000
b1000100 2
1(
#900000
0(
b11011010110101 )
b11011010110101 .
b11011010110101 5
b11111000100011 *
b11100010010010 '
r-1902.115656587058 -
b1010000 ,
#905000
b1000101 2
1(
#910000
0(
b11100100011110 )
b11100100011110 .
b11100100011110 5
b1100001 *
b11100010111101 '
r-1859.556136758361 -
b1010001 ,
#915000
b1000110 2
1(
#920000
0(
b11011110100000 )
b11011110100000 .
b11011110100000 5
b11111010110001 *
b11100011101111 '
r-1809.657810801853 -
b1010010 ,
#925000
b1000111 2
1(
#930000
0(
b11011111010000 )
b11011111010000 .
b11011111010000 5
b11111010101000 *
b11100100101000 '
r-1752.617604281144 -
b1010011 ,
#935000
b1001000 2
1(
#940000
0(
b11100010000111 )
b11100010000111 .
b11100010000111 5
b11111100011111 *
b11100101101000 '
r-1688.660628452017 -
b1010100 ,
#945000
b1001001 2
1(
#950000
0(
b11011110000111 )
b11011110000111 .
b11011110000111 5
b11110111011001 *
b11100110101110 '
r-1618.039291852649 -
b1010101 ,
#955000
b1001010 2
1(
#960000
0(
b11100101111001 )
b11100101111001 .
b11100101111001 5
b11111101111110 *
b11100111111011 '
r-1541.032304164096 -
b1010110 ,
#965000
b1001011 2
1(
#970000
0(
b11101011110011 )
b11101011110011 .
b11101011110011 5
b10100100 *
b11101001001111 '
r-1457.943576272385 -
b1010111 ,
#975000
b1001100 2
1(
#980000
0(
b11100001100001 )
b11100001100001 .
b11100001100001 5
b11110110111010 *
b11101010100111 '
r-1369.101020873102 -
b1011000 ,
#985000
b1001101 2
1(
#990000
0(
b11101010100110 )
b11101010100110 .
b11101010100110 5
b11111110100000 *
b11101100000110 '
r-1274.855258351992 -
b1011001 ,
#995000
b1001110 2
1(
#1000000
0(
b11100110011000 )
b11100110011000 .
b11100110011000 5
b11111000101111 *
b11101101101001 '
r-1175.578233048796 -
b1011010 ,
#1005000
b1001111 2
1(
#1010000
0(
b11101110000110 )
b11101110000110 .
b11101110000110 5
b11111110110101 *
b11101111010001 '
r-1071.66174536537 -
b1011011 ,
#1015000
b1010000 2
1(
#1020000
0(
b11110001110111 )
b11110001110111 .
b11110001110111 5
b111010 *
b11110000111101 '
r-963.5159055110857 -
b1011100 ,
#1025000
b1010001 2
1(
#1030000
0(
b11101111000011 )
b11101111000011 .
b11101111000011 5
b11111100010110 *
b11110010101101 '
r-851.5675149879454 -
b1011101 ,
#1035000
b1010010 2
1(
#1040000
0(
b11110011100101 )
b11110011100101 .
b11110011100101 5
b11111111000101 *
b11110100100000 '
r-736.2583822028715 -
b1011110 ,
#1045000
b1010011 2
1(
#1050000
0(
b11110101100111 )
b11110101100111 .
b11110101100111 5
b11111111010001 *
b11110110010110 '
r-618.0435788547234 -
b1011111 ,
#1055000
b1010100 2
1(
#1060000
0(
b11111000110110 )
b11111000110110 .
b11111000110110 5
b100111 *
b11111000001111 '
r-497.389643977234 -
b1100000 ,
#1065000
b1010101 2
1(
#1070000
0(
b11110011100101 )
b11110011100101 .
b11110011100101 5
b11111001011011 *
b11111010001010 '
r-374.7727427256849 -
b1100001 ,
#1075000
b1010110 2
1(
#1080000
0(
b11111011000011 )
b11111011000011 .
b11111011000011 5
b11111110111101 *
b11111100000110 '
r-250.6767871737638 -
b1100010 ,
#1085000
b1010111 2
1(
#1090000
0(
b11110111010011 )
b11110111010011 .
b11110111010011 5
b11111001010000 *
b11111110000011 '
r-125.5915265369113 -
b1100011 ,
#1095000
b1011000 2
1(
#1100000
0(
b11111101100011 )
b11111101100011 .
b11111101100011 5
b11111101100011 *
b0 '
r-0.01061435917337353 -
b1100100 ,
#1105000
b1011001 2
1(
#1110000
0(
b1001110 )
b1001110 .
b1001110 5
b11111111010001 *
b1111101 '
r125.570339708522 -
b1100101 ,
#1115000
b1011010 2
1(
#1120000
0(
b10001 )
b10001 .
b10001 5
b11111100010111 *
b11111010 '
r250.6557258499196 -
b1100110 ,
#1125000
b1011011 2
1(
#1130000
0(
b10111000 )
b10111000 .
b10111000 5
b11111101000010 *
b101110110 '
r374.7518900256701 -
b1100111 ,
#1135000
b1011100 2
1(
#1140000
0(
b1010110001 )
b1010110001 .
b1010110001 5
b11000000 *
b111110001 '
r497.3690821969885 -
b1101000 ,
#1145000
b1011101 2
1(
#1150000
0(
b100011000 )
b100011000 .
b100011000 5
b11111010101110 *
b1001101010 '
r618.023389142068 -
b1101001 ,
#1155000
b1011110 2
1(
#1160000
0(
b101110110 )
b101110110 .
b101110110 5
b11111010010110 *
b1011100000 '
r736.2386442372388 -
b1101010 ,
#1165000
b1011111 2
1(
#1170000
0(
b1000100111 )
b1000100111 .
b1000100111 5
b11111011010100 *
b1101010011 '
r851.5483066659382 -
b1101011 ,
#1175000
b1100000 2
1(
#1180000
0(
b1100010101 )
b1100010101 .
b1100010101 5
b11111101010010 *
b1111000011 '
r963.4973026390476 -
b1101100 ,
#1185000
b1100001 2
1(
#1190000
0(
b111101101 )
b111101101 .
b111101101 5
b11110110111110 *
b10000101111 '
r1071.643821360214 -
b1101101 ,
#1195000
b1100010 2
1(
#1200000
0(
b10001000010 )
b10001000010 .
b10001000010 5
b11111110101011 *
b10010010111 '
r1175.561058648263 -
b1101110 ,
#1205000
b1100011 2
10
1(
#1210000
0(
b1101100101 )
b1101100101 .
b1101100101 5
b11111001101011 *
b10011111010 '
r1274.838901335478 -
b1101111 ,
#1215000
b1 8
b1100011 !
b1100011 3
b0 2
14
1(
#1220000
0(
b10010000000 )
b10010000000 .
b10010000000 5
b11111100100111 *
b10101011001 '
r1369.085545794173 -
b1110000 ,
#1225000
b1 2
1(
#1230000
0(
b10001111100 )
b10001111100 .
b10001111100 5
b11111011001011 *
b10110110001 '
r1457.929044204001 -
b1110001 ,
#1235000
b10 2
1(
#1240000
0(
b10001101100 )
b10001101100 .
b10001101100 5
b11111001100111 *
b11000000101 '
r1541.018772457596 -
b1110010 ,
#1245000
b11 2
1(
#1250000
0(
b10111111110 )
b10111111110 .
b10111111110 5
b11111110101100 *
b11001010010 '
r1618.026813911407 -
b1110011 ,
#1255000
b100 2
1(
#1260000
0(
b11100000111 )
b11100000111 .
b11100000111 5
b1101111 *
b11010011000 '
r1688.649253520684 -
b1110100 ,
#1265000
b101 2
1(
#1270000
0(
b10011001011 )
b10011001011 .
b10011001011 5
b11110111110011 *
b11011011000 '
r1752.6073772513 -
b1110101 ,
#1275000
b110 2
1(
#1280000
0(
b10100011111 )
b10100011111 .
b10100011111 5
b11111000001110 *
b11100010001 '
r1809.648772034844 -
b1110110 ,
#1285000
b111 2
1(
#1290000
0(
b11110110101 )
b11110110101 .
b11110110101 5
b1110010 *
b11101000011 '
r1859.548321926012 -
b1110111 ,
#1295000
b1000 2
1(
#1300000
0(
b11100011111 )
b11100011111 .
b11100011111 5
b11111110110001 *
b11101101110 '
r1902.10909653089 -
b1111000 ,
#1305000
b1001 2
1(
#1310000
0(
b10101000110 )
b10101000110 .
b10101000110 5
b11110110110101 *
b11110010001 '
r1937.16312819994 -
b1111001 ,
#1315000
b1010 2
1(
#1320000
0(
b11001001110 )
b11001001110 .
b11001001110 5
b11111010100010 *
b11110101100 '
r1964.572074918456 -
b1111010 ,
#1325000
b1011 2
1(
#1330000
0(
b10110101101 )
b10110101101 .
b10110101101 5
b11110111101101 *
b11111000000 '
r1984.227766278372 -
b1111011 ,
#1335000
b1100 2
1(
#1340000
0(
b11000111001 )
b11000111001 .
b11000111001 5
b11111001101101 *
b11111001100 '
r1996.052630376723 -
b1111100 ,
#1345000
b1101 2
1(
#1350000
0(
b10111000110 )
b10111000110 .
b10111000110 5
b11110111110111 *
b11111001111 '
r1999.99999995599 -
b1111101 ,
#1355000
b1110 2
1(
#1360000
0(
b11100111101 )
b11100111101 .
b11100111101 5
b11111101110001 *
b11111001100 '
r1996.054296578135 -
b1111110 ,
#1365000
b1111 2
1(
#1370000
0(
b100001011100 )
b100001011100 .
b100001011100 5
b10011100 *
b11111000000 '
r1984.231092105471 -
b1111111 ,
#1375000
b10000 2
1(
#1380000
0(
b11001100100 )
b11001100100 .
b11001100100 5
b11111010111000 *
b11110101100 '
r1964.577047245744 -
b10000000 ,
#1385000
b10001 2
1(
#1390000
0(
b11110100011 )
b11110100011 .
b11110100011 5
b10010 *
b11110010001 '
r1937.169727403946 -
b10000001 ,
#1395000
b10010 2
1(
#1400000
0(
b11011110001 )
b11011110001 .
b11011110001 5
b11111110000011 *
b11101101110 '
r1902.117296567615 -
b10000010 ,
#1405000
b10011 2
1(
#1410000
0(
b11010001001 )
b11010001001 .
b11010001001 5
b11111101000110 *
b11101000011 '
r1859.558090433713 -
b10000011 ,
#1415000
b10100 2
1(
#1420000
0(
b11110000101 )
b11110000101 .
b11110000101 5
b1110100 *
b11100010001 '
r1809.660070461748 -
b10000100 ,
#1425000
b10101 2
1(
#1430000
0(
b10101111010 )
b10101111010 .
b10101111010 5
b11111010100010 *
b11011011000 '
r1752.620161007752 -
b10000101 ,
#1435000
b10110 2
1(
#1440000
0(
b10110001101 )
b10110001101 .
b10110001101 5
b11111011110101 *
b11010011000 '
r1688.663472155125 -
b10000110 ,
#1445000
b10111 2
1(
#1450000
0(
b10101111101 )
b10101111101 .
b10101111101 5
b11111100101011 *
b11001010010 '
r1618.042411309474 -
b10000111 ,
#1455000
b11000 2
1(
#1460000
0(
b10111010011 )
b10111010011 .
b10111010011 5
b11111111001110 *
b11000000101 '
r1541.035687063592 -
b10001000 ,
#1465000
b11001 2
1(
#1470000
0(
b10110110111 )
b10110110111 .
b10110110111 5
b110 *
b10110110001 '
r1457.947209263815 -
b10001001 ,
#1475000
b11010 2
1(
#1480000
0(
b10010001000 )
b10010001000 .
b10010001000 5
b11111100101111 *
b10101011001 '
r1369.104889618735 -
b10001010 ,
#1485000
b11011 2
1(
#1490000
0(
b1101111100 )
b1101111100 .
b1101111100 5
b11111010000010 *
b10011111010 '
r1274.859347583678 -
b10001011 ,
#1495000
b11100 2
1(
#1500000
0(
b10011110101 )
b10011110101 .
b10011110101 5
b1011110 *
b10010010111 '
r1175.582526628237 -
b10001100 ,
#1505000
b11101 2
1(
#1510000
0(
b1000101111 )
b1000101111 .
b1000101111 5
b11111000000000 *
b10000101111 '
r1071.666226347792 -
b10001101 ,
#1515000
b11110 2
1(
#1520000
0(
b10000000100 )
b10000000100 .
b10000000100 5
b1000001 *
b1111000011 '
r963.5205562121338 -
b10001110 ,
#1525000
b11111 2
1(
#1530000
0(
b111100011 )
b111100011 .
b111100011 5
b11111010010000 *
b1101010011 '
r851.5723170534565 -
b10001111 ,
#1535000
b100000 2
1(
#1540000
0(
b1000011100 )
b1000011100 .
b1000011100 5
b11111100111100 *
b1011100000 '
r736.2633166813172 -
b10010000 ,
#1545000
b100001 2
1(
#1550000
0(
b111010101 )
b111010101 .
b111010101 5
b11111101101011 *
b1001101010 '
r618.0486262720077 -
b10010001 ,
#1555000
b100010 2
1(
#1560000
0(
b11111110101101 )
b11111110101101 .
b11111110101101 5
b11110110111100 *
b111110001 '
r497.3947844135407 -
b10010010 ,
#1565000
b100011 2
1(
#1570000
0(
b1110111 )
b1110111 .
b1110111 5
b11111100000001 *
b101110110 '
r374.7779558940894 -
b10010011 ,
#1575000
b100100 2
1(
